LICENCE.txt
MANIFEST.in
README.rst
setup.py
django_icomoon.egg-info/PKG-INFO
django_icomoon.egg-info/SOURCES.txt
django_icomoon.egg-info/dependency_links.txt
django_icomoon.egg-info/not-zip-safe
django_icomoon.egg-info/requires.txt
django_icomoon.egg-info/top_level.txt
icomoon/__init__.py
icomoon/models.py
icomoon/settings.py
icomoon/store.py
icomoon/urls.py
icomoon/utils.py
icomoon/views.py
icomoon/management/__init__.py
icomoon/management/commands/__init__.py
icomoon/management/commands/icomoon_deploy.py
icomoon/templates/icomoon/icon_map.css
icomoon/templates/icomoon/icon_map.scss
icomoon/templates/icomoon/index.html