Metadata-Version: 1.1
Name: django-icomoon
Version: 1.1.0
Summary: 
